{
  "_class": "text",
  "attributedString": {
    "_class": "attributedString",
    "attributes": [
      {
        "_class": "stringAttribute",
        "attributes": {
          "MSAttributedStringColorAttribute": {
            "_class": "color",
            "alpha": 1,
            "blue": 1,
            "green": 1,
            "red": 1
          },
          "MSAttributedStringFontAttribute": {
            "_class": "fontDescriptor",
            "attributes": {
              "name": "Helvetica-Bold",
              "size": 28
            }
          },
          "paragraphStyle": {
            "_class": "paragraphStyle",
            "alignment": 2
          }
        },
        "length": 9,
        "location": 0
      }
    ],
    "string": "SHOP NOW!"
  },
  "automaticallyDrawOnUnderlyingPath": false,
  "booleanOperation": 0,
  "do_objectID": "442A0BC6-EF45-4DA4-AE8C-6714CA237BAF",
  "dontSynchroniseWithSymbol": false,
  "exportOptions": {
    "_class": "exportOptions",
    "do_objectID": "04EC11E3-06C4-42C5-A014-10C02C50457E",
    "exportFormats": [
    ],
    "includedLayerIds": [
    ],
    "layerOptions": 0,
    "shouldTrim": false
  },
  "flow": {
    "_class": "MSImmutableFlowConnection",
    "animationType": -1,
    "destinationArtboardID": "1A7B7ED3-4AF8-47B5-B677-95C87E377D19",
    "do_objectID": "5CA4BF31-3460-4C97-AC53-9932FFF1312F"
  },
  "frame": {
    "_class": "rect",
    "constrainProportions": false,
    "do_objectID": "04CA9025-FBC2-434B-B9C9-A0A12F5A6947",
    "height": 60,
    "width": 287,
    "x": 241,
    "y": 481
  },
  "glyphBounds": "{{62, 7}, {162, 22}}",
  "isFixedToViewport": false,
  "isFlippedHorizontal": false,
  "isFlippedVertical": false,
  "isLocked": false,
  "isVisible": true,
  "layerListExpandedType": 0,
  "lineSpacingBehaviour": 2,
  "name": "SHOP NOW!",
  "nameIsFixed": false,
  "resizingConstraint": 63,
  "resizingType": 0,
  "rotation": 0,
  "shouldBreakMaskChain": false,
  "style": {
    "_class": "style",
    "do_objectID": "F237B9BD-9196-4DFA-A814-4E5E17B9C6BB",
    "endMarkerType": 0,
    "miterLimit": 10,
    "startMarkerType": 0,
    "textStyle": {
      "_class": "textStyle",
      "do_objectID": "291D2814-5636-4F45-8E4F-3C23CBDA8ECA",
      "encodedAttributes": {
        "MSAttributedStringColorAttribute": {
          "_class": "color",
          "alpha": 1,
          "blue": 1,
          "green": 1,
          "red": 1
        },
        "MSAttributedStringFontAttribute": {
          "_class": "fontDescriptor",
          "attributes": {
            "name": "Helvetica-Bold",
            "size": 28
          }
        },
        "paragraphStyle": {
          "_class": "paragraphStyle",
          "alignment": 2
        }
      },
      "verticalAlignment": 0
    },
    "windingRule": 1
  },
  "textBehaviour": 2,
  "userInfo": {
    "com.animaapp.stc-sketch-plugin": {
      "kModelPropertiesKey": {
        "isAutoWidth": 0
      }
    }
  }
}