{
  "_class": "group",
  "do_objectID": "27AB5797-C88E-40DB-9015-A2D12E16209B",
  "exportOptions": {
    "_class": "exportOptions",
    "exportFormats": [
    ],
    "includedLayerIds": [
    ],
    "layerOptions": 0,
    "shouldTrim": false
  },
  "frame": {
    "_class": "rect",
    "constrainProportions": false,
    "height": 1930,
    "width": 2725,
    "x": 0,
    "y": -7
  },
  "hasClickThrough": false,
  "isFlippedHorizontal": false,
  "isFlippedVertical": false,
  "isLocked": true,
  "isVisible": true,
  "layerListExpandedType": 0,
  "layers": [
    {
      "class": "bitmap",
      "id": "1D3C09AC-D6FF-42A7-9A25-E538F725C46A"
    },
    {
      "class": "shapeGroup",
      "id": "C81732B4-0C7E-4621-8E0F-4C8C7A3E5190"
    }
  ],
  "name": "Background",
  "nameIsFixed": true,
  "resizingConstraint": 63,
  "resizingType": 0,
  "rotation": 0,
  "shouldBreakMaskChain": false,
  "style": {
    "_class": "style",
    "endDecorationType": 0,
    "miterLimit": 10,
    "startDecorationType": 0
  }
}