{
  "_class": "bitmap",
  "clippingMask": "{{0, 0}, {1, 1}}",
  "do_objectID": "6AEA56A4-DF7C-407F-8199-02A6D5822B27",
  "exportOptions": {
    "_class": "exportOptions",
    "do_objectID": "F11F521C-6E26-4569-9D16-92622AF2FF3A",
    "exportFormats": [
    ],
    "includedLayerIds": [
    ],
    "layerOptions": 0,
    "shouldTrim": false
  },
  "fillReplacesImage": false,
  "frame": {
    "_class": "rect",
    "constrainProportions": true,
    "do_objectID": "B5809E9E-E495-4D7A-A308-84B004CE8B08",
    "height": 80,
    "width": 398,
    "x": 548,
    "y": 317
  },
  "image": {
    "_class": "MSJSONFileReference",
    "_ref": "images/4b2a7cd3f0b280d85dd646b90c27449a366b96a3",
    "_ref_class": "MSImageData"
  },
  "isFlippedHorizontal": false,
  "isFlippedVertical": false,
  "isLocked": false,
  "isVisible": true,
  "layerListExpandedType": 0,
  "name": "GeoScientificLtd-300x113",
  "nameIsFixed": false,
  "resizingConstraint": 63,
  "resizingType": 0,
  "rotation": 0,
  "shouldBreakMaskChain": false,
  "style": {
    "_class": "style",
    "do_objectID": "E8704C0B-F7FF-487B-AA75-22CAD05B6FFA",
    "endDecorationType": 0,
    "miterLimit": 10,
    "startDecorationType": 0
  },
  "userInfo": {
    "com.animaapp.stc-sketch-plugin": {
      "kModelPropertiesKey": {
      }
    }
  }
}