{
  "_class": "group",
  "do_objectID": "F97BC967-728A-4FC6-8684-D4D2D8559EE8",
  "exportOptions": {
    "_class": "exportOptions",
    "do_objectID": "CA435902-7F51-4AB6-9CA9-1D287CFF10DC",
    "exportFormats": [
    ],
    "includedLayerIds": [
    ],
    "layerOptions": 0,
    "shouldTrim": false
  },
  "frame": {
    "_class": "rect",
    "constrainProportions": false,
    "do_objectID": "3525BA54-8862-4466-9751-5090D1AD00C5",
    "height": 57,
    "width": 375,
    "x": 0,
    "y": 4269
  },
  "hasClickThrough": false,
  "isFlippedHorizontal": false,
  "isFlippedVertical": false,
  "isLocked": false,
  "isVisible": true,
  "layerListExpandedType": 0,
  "layers": [
    {
      "class": "text",
      "id": "213100AB-5C0A-4F63-A0C7-36AF40585570"
    }
  ],
  "name": "Footer",
  "nameIsFixed": true,
  "resizingConstraint": 63,
  "resizingType": 0,
  "rotation": 0,
  "shouldBreakMaskChain": false,
  "style": {
    "_class": "style",
    "do_objectID": "AA4B8997-6130-4F54-99DC-80F07A1E3322",
    "endDecorationType": 0,
    "miterLimit": 10,
    "startDecorationType": 0
  },
  "userInfo": {
    "com.animaapp.stc-sketch-plugin": {
      "kModelPropertiesKey": {
        "constraints": {
          "automatic": 1,
          "centerHorizontally": {
            "constant": 0,
            "enabled": 1,
            "modelID": "constraint_6b5379d3-b53d-43c8-b884-0710f8322720",
            "model_class": "ADModelConstraint",
            "model_version": 0.1,
            "multiplier": 0
          },
          "modelID": "viewConstraints_4fe5734c-3c71-434e-8900-244a2c43ff8e",
          "model_class": "ADModelViewConstraints",
          "model_version": 0.1,
          "scaleFactor": 1
        }
      }
    }
  }
}